pytest_bdd_splinter/__init__.py
pytest_bdd_splinter/browse.py
pytest_bdd_splinter/forms.py
pytest_bdd_splinter/misc.py
pytest_bdd_splinter/mouse.py
pytest_bdd_splinter/plugin.py
pytest_bdd_splinter/rendering.py
pytest_bdd_splinter/utils.py
pytest_bdd_splinter-0.4.0.dist-info/LICENSE
pytest_bdd_splinter-0.4.0.dist-info/METADATA
pytest_bdd_splinter-0.4.0.dist-info/WHEEL
pytest_bdd_splinter-0.4.0.dist-info/top_level.txt
pytest_bdd_splinter-0.4.0.dist-info/RECORD
