Metadata-Version: 2.1
Name: pytest-bdd-splinter
Version: 0.4.0
Summary: Common steps for pytest bdd and splinter integration
Home-page: https://github.com/labd/pytest-bdd-splinter
Author: Lab Digital
Author-email: opensource@labdigital.nl
License: MIT
Platform: UNKNOWN
Classifier: Development Status :: 5 - Production/Stable
Classifier: Environment :: Web Environment
Classifier: License :: OSI Approved :: MIT License
Classifier: Programming Language :: Python
Classifier: Programming Language :: Python :: 3.6
Classifier: Programming Language :: Python :: 3.7
Requires-Dist: pytest (>=4.0.0)
Requires-Dist: pytest-bdd (>=3.0.0)
Requires-Dist: pytest-splinter (>=2.0.0)
Provides-Extra: docs
Requires-Dist: mkdocs (>=1.0.4) ; extra == 'docs'
Requires-Dist: mkdocs-material (==4.4.0) ; extra == 'docs'
Provides-Extra: test
Requires-Dist: coverage (==4.2) ; extra == 'test'
Requires-Dist: Flask (==1.0.3) ; extra == 'test'
Requires-Dist: isort (==4.2.5) ; extra == 'test'
Requires-Dist: flake8 (==3.0.3) ; extra == 'test'
Requires-Dist: flake8-blind-except (==0.1.1) ; extra == 'test'
Requires-Dist: flake8-debugger (==1.4.0) ; extra == 'test'
